{
  "id": "m33",
  "name": "M33Triangulum",
  "distance": 20,
  "galactic_radius": 17,
  "mass": 7100000000,
  "accel": 1,
  "mass_model": {
    "bulge": {
      "M": 400000000,
      "a": 0.18
    },
    "disk": {
      "M": 3500000000,
      "Rd": 1.6
    },
    "gas": {
      "M": 3200000000,
      "Rd": 4.0
    }
  },
  "observations": [
    {
      "r": 0.5,
      "v": 30,
      "err": 5
    },
    {
      "r": 1,
      "v": 38,
      "err": 8
    },
    {
      "r": 1.5,
      "v": 55,
      "err": 7
    },
    {
      "r": 2,
      "v": 68,
      "err": 8
    },
    {
      "r": 3,
      "v": 88,
      "err": 6
    },
    {
      "r": 4,
      "v": 100,
      "err": 7
    },
    {
      "r": 5,
      "v": 105,
      "err": 5
    },
    {
      "r": 6,
      "v": 108,
      "err": 6
    },
    {
      "r": 7,
      "v": 108,
      "err": 5
    },
    {
      "r": 8,
      "v": 108,
      "err": 6
    },
    {
      "r": 9,
      "v": 110,
      "err": 6
    },
    {
      "r": 10,
      "v": 115,
      "err": 7
    },
    {
      "r": 11,
      "v": 117,
      "err": 6
    },
    {
      "r": 12,
      "v": 120,
      "err": 7
    },
    {
      "r": 14,
      "v": 125,
      "err": 7
    },
    {
      "r": 15,
      "v": 128,
      "err": 8
    },
    {
      "r": 17,
      "v": 130,
      "err": 8
    }
  ],
  "references": [
    "Corbelli & Salucci 2000 MNRAS 311 441",
    "Corbelli 2003 MNRAS 342 199",
    "Corbelli 2014 A&A (VLA+GBT)"
  ]
}